mypy_exhaustive_check/__init__.py
mypy_exhaustive_check/py.typed
mypy_exhaustive_check/dispatcher/__init__.py
mypy_exhaustive_check/dispatcher/dispatcher.py
mypy_exhaustive_check/plugins/__init__.py
mypy_exhaustive_check/plugins/base/__init__.py
mypy_exhaustive_check/plugins/base/check_type.py
mypy_exhaustive_check/plugins/base/plugin.py
mypy_exhaustive_check/plugins/dict_check/__init__.py
mypy_exhaustive_check/plugins/dict_check/errors.py
mypy_exhaustive_check/plugins/dict_check/plugin.py
mypy_exhaustive_check-1.0.0.dist-info/LICENSE
mypy_exhaustive_check-1.0.0.dist-info/METADATA
mypy_exhaustive_check-1.0.0.dist-info/WHEEL
mypy_exhaustive_check-1.0.0.dist-info/top_level.txt
mypy_exhaustive_check-1.0.0.dist-info/RECORD
