Metadata-Version: 2.1
Name: mypy-exhaustive-check
Version: 1.0.0
Author-email: "Ezequiel L. Castaño" <castanoezequielleonardo@gmail.com>
License: MIT
Project-URL: homepage, https://github.com/elc/mypy-exhaustive-check
Project-URL: documentation, https://github.com/elc/mypy-exhaustive-check
Project-URL: repository, https://github.com/elc/mypy-exhaustive-check
Project-URL: changelog, https://github.com/ELC/mypy-exhaustive-check/blob/master/CHANGELOG.md
Classifier: Development Status :: 4 - Beta
Classifier: Programming Language :: Python
Classifier: License :: OSI Approved :: MIT License
Classifier: Intended Audience :: Developers
Classifier: Natural Language :: English
Classifier: Operating System :: OS Independent
Classifier: Topic :: Software Development :: Quality Assurance
Classifier: Typing :: Typed
Requires-Python: >=3.9
License-File: LICENSE
Requires-Dist: mypy ~=1.0
Requires-Dist: typing-extensions ~=4.0
